Metadata-Version: 2.1
Name: tgapp-mailtemplates
Version: 0.13.8
Summary: Email template management for web applications
Home-page: https://github.com/axant/tgapp-mailtemplates
Author: Marco Bosio
Author-email: marco.bosio@axant.it
License: UNKNOWN
Keywords: turbogears2.application
Platform: UNKNOWN
Provides-Extra: testing
Provides-Extra: celery
Provides-Extra: asyncjob
